xypattern/__init__.py
xypattern/auto_background.py
xypattern/combine.py
xypattern/pattern.py
xypattern/scripts/__init__.py
xypattern/scripts/stitch_patterns.py
xypattern/util/__init__.py
xypattern/util/signal.py
xypattern/util/smooth_bruckner.cpython-311-darwin.so
xypattern/util/smooth_bruckner.pyx
xypattern/util/smooth_bruckner_py.py
xypattern-1.2.3.dist-info/METADATA
xypattern-1.2.3.dist-info/WHEEL
xypattern-1.2.3.dist-info/entry_points.txt
xypattern-1.2.3.dist-info/licenses/LICENSE.txt
xypattern-1.2.3.dist-info/RECORD
