Metadata-Version: 2.1
Name: xypattern
Version: 1.2.3
Summary: Library for handling x-y pattern data.
License: MIT
Author: Clemens Prescher
Author-email: clemens.prescher@gmail.com
Requires-Python: >=3.8,<3.14
Classifier: Intended Audience :: Science/Research
Classifier: License :: OSI Approved :: MIT License
Classifier: Operating System :: OS Independent
Classifier: Programming Language :: Python
Classifier: Programming Language :: Python :: 3
Classifier: Programming Language :: Python :: 3.8
Classifier: Programming Language :: Python :: 3.9
Classifier: Programming Language :: Python :: 3.10
Classifier: Programming Language :: Python :: 3.11
Classifier: Programming Language :: Python :: 3.12
Classifier: Programming Language :: Python :: 3.13
Classifier: Topic :: Scientific/Engineering
Classifier: Topic :: Scientific/Engineering :: Chemistry
Classifier: Topic :: Scientific/Engineering :: Information Analysis
Classifier: Topic :: Scientific/Engineering :: Physics
Classifier: Topic :: Scientific/Engineering :: Visualization
Requires-Dist: numpy (>=1.24.0,<2.0.0) ; python_version >= "3.8" and python_version < "3.9"
Requires-Dist: numpy (>=1.26,<3.0) ; python_version >= "3.9"
Requires-Dist: scipy (>=1.11.3,<2.0.0) ; python_version >= "3.10"
Requires-Dist: scipy (>=1.9.3,<2.0.0) ; python_version < "3.10"
